blocksolver/__init__.py
blocksolver/blqmr.py
blocksolver-0.8.5.dist-info/METADATA
blocksolver-0.8.5.dist-info/WHEEL
blocksolver-0.8.5.dist-info/top_level.txt
blocksolver-0.8.5.dist-info/RECORD
