Metadata-Version: 2.4
Name: blocksolver
Version: 0.8.5
Summary: Block Quasi-Minimal-Residual sparse linear solver
Home-page: https://blit.sourceforge.net
Author: Qianqian Fang
Author-email: Qianqian Fang <q.fang@neu.edu>
License: BSD-3-Clause OR LGPL-3.0-or-later OR GPL-3.0-or-later
Project-URL: Homepage, https://blit.sourceforge.net
Project-URL: Repository, https://github.com/fangq/blocksolver
Project-URL: Documentation, https://blit.sourceforge.net
Project-URL: Bug Tracker, https://github.com/fangq/blocksolver/issues
Keywords: sparse,linear-algebra,iterative-solver,qmr,fortran,umfpack
Classifier: Development Status :: 4 - Beta
Classifier: Intended Audience :: Science/Research
Classifier: License :: OSI Approved :: BSD License
Classifier: License :: OSI Approved :: GNU Lesser General Public License v3 or later (LGPLv3+)
Classifier: License :: OSI Approved :: GNU General Public License v3 or later (GPLv3+)
Classifier: Operating System :: OS Independent
Classifier: Operating System :: POSIX :: Linux
Classifier: Operating System :: MacOS
Classifier: Operating System :: Microsoft :: Windows
Classifier: Programming Language :: Fortran
Classifier: Programming Language :: Python :: 3
Classifier: Programming Language :: Python :: 3.8
Classifier: Programming Language :: Python :: 3.9
Classifier: Programming Language :: Python :: 3.10
Classifier: Programming Language :: Python :: 3.11
Classifier: Programming Language :: Python :: 3.12
Classifier: Programming Language :: Python :: 3.13
Classifier: Topic :: Scientific/Engineering :: Mathematics
Requires-Python: >=3.8
Requires-Dist: numpy>=1.20
Requires-Dist: scipy>=1.0
Provides-Extra: fast
Requires-Dist: numba>=0.50; extra == "fast"
Provides-Extra: test
Requires-Dist: pytest>=6.0; extra == "test"
Provides-Extra: dev
Requires-Dist: pytest>=6.0; extra == "dev"
Requires-Dist: build; extra == "dev"
Requires-Dist: twine; extra == "dev"
Dynamic: author
Dynamic: home-page
Dynamic: requires-python
